mangaplus/__init__.py
mangaplus/constants.py
mangaplus/protocol/mangaplus_api.proto
mangaplus/protocol/mangaplus_api_pb2.py
mangaplus/protocol/mangaplus_api_pb2.pyi
mangaplus/shueisha.py
mangaplus/utils.py
mangaplus-1.23.2.dist-info/LICENSE
mangaplus-1.23.2.dist-info/METADATA
mangaplus-1.23.2.dist-info/WHEEL
mangaplus-1.23.2.dist-info/RECORD
