Metadata-Version: 2.1
Name: mangaplus
Version: 1.23.2
Summary: Python client for MangaPlus to access manga content and interact with the API.
Home-page: https://github.com/hyugogirubato/mangaplus
License: GPL
Keywords: python,client,manga,ebooks,mangaplus,shueisha
Author: hyugogirubato
Author-email: 65763543+hyugogirubato@users.noreply.github.com
Requires-Python: >=3.8,<4.0
Classifier: Development Status :: 5 - Production/Stable
Classifier: Intended Audience :: Developers
Classifier: Intended Audience :: End Users/Desktop
Classifier: License :: Other/Proprietary License
Classifier: Natural Language :: English
Classifier: Operating System :: OS Independent
Classifier: Programming Language :: Python :: 3
Classifier: Programming Language :: Python :: 3.8
Classifier: Programming Language :: Python :: 3.9
Classifier: Programming Language :: Python :: 3.10
Classifier: Programming Language :: Python :: 3.11
Classifier: Programming Language :: Python :: 3.12
Classifier: Topic :: Multimedia :: Graphics
Classifier: Topic :: Software Development :: Libraries :: Python Modules
Classifier: Topic :: Text Processing :: Linguistic
Classifier: Topic :: Utilities
Requires-Dist: protobuf (>=5.29.5,<6.0.0)
Requires-Dist: requests (>=2.32.3)
Project-URL: Changelog, https://github.com/hyugogirubato/mangaplus/blob/main/CHANGELOG.md
Project-URL: Issues, https://github.com/hyugogirubato/mangaplus/issues
Project-URL: Repository, https://github.com/hyugogirubato/mangaplus
